sermos/__init__.py
sermos/celery.py
sermos/celery_beat.py
sermos/cloud.py
sermos/constants.py
sermos/deploy.py
sermos/generators.py
sermos/logging_config.py
sermos/pipeline_config_schema.py
sermos/proxy.py
sermos/schedule_config_schema.py
sermos/sermos_yaml.py
sermos/cli/__init__.py
sermos/cli/config_server.py
sermos/cli/core.py
sermos/cli/deploy.py
sermos/cli/proxy.py
sermos/cli/version.py
sermos/flask/__init__.py
sermos/flask/decorators.py
sermos/flask/flask_sermos.py
sermos/flask/api/__init__.py
sermos/flask/api/pipelines.py
sermos/flask/api/schedules.py
sermos/flask/api/utils.py
sermos/lib/__init__.py
sermos/lib/config_server.py
sermos/static/logos/sermos-favicon-16x16.png
sermos/static/logos/sermos-favicon-32x32.png
sermos/static/logos/sermos-favicon-64x64.png
sermos/static/logos/sermos_black_RGB.png
sermos/static/logos/sermos_light_purple_RGB.png
sermos/static/logos/sermos_purple_RGB.png
sermos/static/logos/sermos_white_RGB.png
sermos/static/swagger/sermos-swagger.css
sermos/static/swagger/theme-material.css
sermos/templates/swagger/swagger_ui.html
sermos/utils/__init__.py
sermos/utils/config_utils.py
sermos/utils/generic_utils.py
sermos/utils/graph_utils.py
sermos/utils/module_utils.py
sermos/utils/smorest.py
sermos/utils/task_utils.py
tests/fixtures/__init__.py
tests/fixtures/s3_fixtures.py
sermos-3.0.0.dist-info/LICENSE
sermos-3.0.0.dist-info/METADATA
sermos-3.0.0.dist-info/WHEEL
sermos-3.0.0.dist-info/entry_points.txt
sermos-3.0.0.dist-info/top_level.txt
sermos-3.0.0.dist-info/RECORD
