Metadata-Version: 2.1
Name: sermos
Version: 3.0.0
Summary: Sermos - Machine Learning for the Real World
Home-page: https://gitlab.com/sermos/sermos
Author: Sermos, LLC
License: Apache License 2.0
Platform: UNKNOWN
License-File: LICENSE
Requires-Dist: PyYAML (>=5.2)
Requires-Dist: marshmallow (<4,>=3.2.1)
Requires-Dist: click
Requires-Dist: requests (>=2.24.0)
Requires-Dist: croniter (<2,>=1.0.15)
Provides-Extra: build
Requires-Dist: wheel ; extra == 'build'
Requires-Dist: twine ; extra == 'build'
Provides-Extra: dev
Requires-Dist: honcho (>=1.0.1) ; extra == 'dev'
Requires-Dist: awscli (>=1.11) ; extra == 'dev'
Requires-Dist: pylint (>=2.5.3) ; extra == 'dev'
Requires-Dist: pip-licenses ; extra == 'dev'
Provides-Extra: docs
Requires-Dist: sphinx (>=3.0.2) ; extra == 'docs'
Requires-Dist: boto3 (>=1.11) ; extra == 'docs'
Requires-Dist: celery (==5.1.2) ; extra == 'docs'
Provides-Extra: flask
Requires-Dist: Flask (>2) ; extra == 'flask'
Requires-Dist: MarkupSafe (>2) ; extra == 'flask'
Requires-Dist: flask-smorest (>=0.40.0) ; extra == 'flask'
Provides-Extra: generators
Requires-Dist: boto3 (>=1.11) ; extra == 'generators'
Provides-Extra: proxy
Requires-Dist: PyJWT (<3,>=2.1.0) ; extra == 'proxy'
Requires-Dist: cryptography (<4,>=3.4.7) ; extra == 'proxy'
Provides-Extra: test
Requires-Dist: pytest-cov (<3,>=2.6.1) ; extra == 'test'
Requires-Dist: tox (<4,>=3.14.1) ; extra == 'test'
Requires-Dist: mock (<2,>=1) ; extra == 'test'
Requires-Dist: moto ; extra == 'test'
Requires-Dist: responses (<0.11,>=0.10.16) ; extra == 'test'
Requires-Dist: fakeredis (>=1.0.5) ; extra == 'test'
Requires-Dist: importlib-metadata (<5,>=4.12) ; extra == 'test'
Provides-Extra: web
Requires-Dist: gunicorn ; extra == 'web'
Requires-Dist: gevent ; extra == 'web'
Provides-Extra: workers
Requires-Dist: celery[redis] (>=5.1.2) ; extra == 'workers'
Requires-Dist: networkx (>=2.4) ; extra == 'workers'
Requires-Dist: redis (>=3.3.11) ; extra == 'workers'
Requires-Dist: rhodb[redis] (>=5.1.1) ; extra == 'workers'
Requires-Dist: sermos-tools (>=0.3.0) ; extra == 'workers'
Requires-Dist: boto3 (>=1.11) ; extra == 'workers'
